polyphy/polyphy.py
polyphy/core/common.py
polyphy/core/discrete2D.py
polyphy/core/discrete3D.py
polyphy/kernel/common.py
polyphy/kernel/discrete2D.py
polyphy/kernel/discrete3D.py
polyphy/pipelines/common.py
polyphy/pipelines/discrete2D.py
polyphy/pipelines/discrete3D.py
polyphy/utils/cli_helper.py
polyphy/utils/gui_helper.py
polyphy/utils/logger.py
PolyPhyPy-0.0.1.dist-info/LICENSE
PolyPhyPy-0.0.1.dist-info/METADATA
PolyPhyPy-0.0.1.dist-info/WHEEL
PolyPhyPy-0.0.1.dist-info/entry_points.txt
PolyPhyPy-0.0.1.dist-info/top_level.txt
PolyPhyPy-0.0.1.dist-info/RECORD
