Metadata-Version: 2.1
Name: PolyPhyPy
Version: 0.0.1
Summary: description for polyphy
Home-page: https://github.com/PolyPhyHub/PolyPhy
Author: Oskar Elek
Author-email: Oskar Elek <oskar.elek@gmail.com>
Maintainer-email: Prashant Jha <prashant.bits01@gmail.com>
License: MIT License
Project-URL: Documentation, https://github.com/PolyPhyHub/PolyPhy
Project-URL: Source, https://github.com/PolyPhyHub/PolyPhy
Keywords: polyphy
Platform: any
Classifier: Development Status :: 4 - Beta
Classifier: Programming Language :: Python
Requires-Python: >=3.7
License-File: LICENSE
Requires-Dist: pytest
Requires-Dist: pytest-cov
Requires-Dist: importlib-metadata ; python_version < "3.8"
Provides-Extra: testing
Requires-Dist: setuptools ; extra == 'testing'
Requires-Dist: pytest ; extra == 'testing'
Requires-Dist: pytest-cov ; extra == 'testing'
